openrouter_mcp_bridge-1.0.0.dist-info/licenses/LICENSE
src/__init__.py
src/__main__.py
src/mcp_server.py
openrouter_mcp_bridge-1.0.0.dist-info/METADATA
openrouter_mcp_bridge-1.0.0.dist-info/WHEEL
openrouter_mcp_bridge-1.0.0.dist-info/entry_points.txt
openrouter_mcp_bridge-1.0.0.dist-info/top_level.txt
openrouter_mcp_bridge-1.0.0.dist-info/RECORD
