Metadata-Version: 2.4
Name: openrouter-mcp-bridge
Version: 1.0.0
Summary: Lightweight MCP server bridging Claude Code to OpenRouter API
Author-email: htooayelwinict <htooayelwinict@gmail.com>, "Shelakh (original author)" <info@shelakh.com>
License-Expression: MIT
Project-URL: Homepage, https://github.com/htooayelwinict/open-bridge
Project-URL: Repository, https://github.com/htooayelwinict/open-bridge
Project-URL: Issues, https://github.com/htooayelwinict/open-bridge/issues
Keywords: mcp,openrouter,ai,coding,assistant,async,http
Classifier: Development Status :: 5 - Production/Stable
Classifier: Intended Audience :: Developers
Classifier: Programming Language :: Python :: 3
Classifier: Programming Language :: Python :: 3.10
Classifier: Programming Language :: Python :: 3.11
Classifier: Programming Language :: Python :: 3.12
Classifier: Topic :: Software Development :: Libraries :: Python Modules
Classifier: Topic :: Scientific/Engineering :: Artificial Intelligence
Requires-Python: >=3.10
License-File: LICENSE
Requires-Dist: mcp>=1.0.0
Requires-Dist: httpx>=0.27.0
Requires-Dist: python-dotenv>=1.0.0
Dynamic: license-file
